expandex/__init__.py
expandex/main.py
expandex-0.0.1.dist-info/LICENSE
expandex-0.0.1.dist-info/METADATA
expandex-0.0.1.dist-info/WHEEL
expandex-0.0.1.dist-info/top_level.txt
expandex-0.0.1.dist-info/RECORD
