Metadata-Version: 2.1
Name: expandex
Version: 0.0.1
Summary: Find images similar to a given source image
Home-page: https://github.com/manbehindthemadness/expandex
Author: Manbehindthemadness
Author-email: manbehindthemadness@gmail.com
Classifier: Programming Language :: Python :: 3
Classifier: License :: OSI Approved :: Apache Software License
Classifier: Operating System :: OS Independent
Requires-Python: >=3.10
License-File: LICENSE
Requires-Dist: opencv-python
Requires-Dist: Pillow
Requires-Dist: numpy
Requires-Dist: requests
Requires-Dist: cloudscraper
Requires-Dist: antidupe
Requires-Dist: featurecrop
Requires-Dist: playwright
